semaphore_sms/__init__.py
semaphore_sms/client.py
semaphore_sms/exceptions.py
semaphore_sms/http.py
semaphore_sms-1.0.0.dist-info/METADATA
semaphore_sms-1.0.0.dist-info/WHEEL
semaphore_sms-1.0.0.dist-info/licenses/LICENSE
semaphore_sms-1.0.0.dist-info/RECORD
