Metadata-Version: 2.1
Name: semaphore-sms
Version: 1.0.0
Summary: API wrapper for https://semaphore.co/
Project-URL: Homepage, https://github.com/sbenemerito/semaphore-sms
Project-URL: Issues, https://github.com/sbenemerito/semaphore-sms/issues
Project-URL: Semaphore SMS Gateway, https://semaphore.co/
Author-email: Sam Benemerito <sbbenemerito@gmail.com>
License-File: LICENSE
Keywords: semaphore,semaphore ph,semaphore sms
Classifier: License :: OSI Approved :: MIT License
Classifier: Operating System :: OS Independent
Classifier: Programming Language :: Python :: 3.7
Classifier: Programming Language :: Python :: 3.8
Classifier: Programming Language :: Python :: 3.9
Classifier: Programming Language :: Python :: 3.10
Classifier: Programming Language :: Python :: 3.11
Classifier: Topic :: Communications :: Telephony
Classifier: Topic :: Software Development :: Libraries :: Python Modules
Requires-Python: >=3.7.0
Requires-Dist: requests>=2.0.0
